<?xml version="1.0" encoding="utf-8"?>
<ECSchema schemaName="IfcApplicationDomain_V3Conversion" nameSpacePrefix="ifcv3" version="1.0" xmlns="http://www.bentley.com/schemas/Bentley.ECXML.2.0">
    <ECSchemaReference name="ECv3ConversionAttributes" version="01.00" prefix="V2ToV3" />
    <ECCustomAttributes>
        <ResolvePropertyNameConflicts xmlns="ECv3ConversionAttributes.01.00" />
        <ResolveClassNameConflicts xmlns="ECv3ConversionAttributes.01.00" />
    </ECCustomAttributes>
    <ECClass typeName="PSet_Application_AirDistribution" isDomainClass="True">
        <ECCustomAttributes>
            <ForceEntityClass xmlns="ECv3ConversionAttributes.01.00" />
        </ECCustomAttributes>
    </ECClass>
    <ECClass typeName="PSet_Application_AirHandling" isDomainClass="True">
        <ECCustomAttributes>
            <ForceEntityClass xmlns="ECv3ConversionAttributes.01.00" />
        </ECCustomAttributes>
    </ECClass>
    <ECClass typeName="PSet_Application_Building" isDomainClass="True">
        <ECCustomAttributes>
            <ForceEntityClass xmlns="ECv3ConversionAttributes.01.00" />
        </ECCustomAttributes>
    </ECClass>
    <ECClass typeName="PSet_Application__ControllerTypeProportional" isDomainClass="True">
        <ECCustomAttributes>
            <ForceEntityClass xmlns="ECv3ConversionAttributes.01.00" />
        </ECCustomAttributes>
    </ECClass>
    <ECClass typeName="PSet_Application__ControllerTypeTwoPosition" isDomainClass="True">
        <ECCustomAttributes>
            <ForceEntityClass xmlns="ECv3ConversionAttributes.01.00" />
        </ECCustomAttributes>
    </ECClass>
    <ECClass typeName="PSet_Application_CustomParamAngularElbow" isDomainClass="True">
        <ECCustomAttributes>
            <ForceEntityClass xmlns="ECv3ConversionAttributes.01.00" />
        </ECCustomAttributes>
    </ECClass>
    <ECClass typeName="PSet_Application_CustomParamCap" isDomainClass="True">
        <ECCustomAttributes>
            <ForceEntityClass xmlns="ECv3ConversionAttributes.01.00" />
        </ECCustomAttributes>
    </ECClass>
    <ECClass typeName="PSet_Application_CustomParamDiffuser" isDomainClass="True">
        <ECCustomAttributes>
            <ForceEntityClass xmlns="ECv3ConversionAttributes.01.00" />
        </ECCustomAttributes>
    </ECClass>
    <ECClass typeName="PSet_Application_CustomParamFans" isDomainClass="True">
        <ECCustomAttributes>
            <ForceEntityClass xmlns="ECv3ConversionAttributes.01.00" />
        </ECCustomAttributes>
    </ECClass>
    <ECClass typeName="PSet_Application_CustomParamFCU" isDomainClass="True">
        <ECCustomAttributes>
            <ForceEntityClass xmlns="ECv3ConversionAttributes.01.00" />
        </ECCustomAttributes>
    </ECClass>
    <ECClass typeName="PSet_Application_CustomParamFlex" isDomainClass="True">
        <ECCustomAttributes>
            <ForceEntityClass xmlns="ECv3ConversionAttributes.01.00" />
        </ECCustomAttributes>
    </ECClass>
    <ECClass typeName="PSet_Application_CustomParamFlexDuct" isDomainClass="True">
        <ECCustomAttributes>
            <ForceEntityClass xmlns="ECv3ConversionAttributes.01.00" />
        </ECCustomAttributes>
    </ECClass>
    <ECClass typeName="PSet_Application_CustomParamOvalDuct" isDomainClass="True">
        <ECCustomAttributes>
            <ForceEntityClass xmlns="ECv3ConversionAttributes.01.00" />
        </ECCustomAttributes>
    </ECClass>
    <ECClass typeName="PSet_Application_CustomParamOvalTee" isDomainClass="True">
        <ECCustomAttributes>
            <ForceEntityClass xmlns="ECv3ConversionAttributes.01.00" />
        </ECCustomAttributes>
    </ECClass>
    <ECClass typeName="PSet_Application_CustomParamOvalTransition" isDomainClass="True">
        <ECCustomAttributes>
            <ForceEntityClass xmlns="ECv3ConversionAttributes.01.00" />
        </ECCustomAttributes>
    </ECClass>
    <ECClass typeName="PSet_Application_CustomParamRectangularDamper" isDomainClass="True">
        <ECCustomAttributes>
            <ForceEntityClass xmlns="ECv3ConversionAttributes.01.00" />
        </ECCustomAttributes>
    </ECClass>
    <ECClass typeName="PSet_Application_CustomParamRectBarsGrille" isDomainClass="True">
        <ECCustomAttributes>
            <ForceEntityClass xmlns="ECv3ConversionAttributes.01.00" />
        </ECCustomAttributes>
    </ECClass>
    <ECClass typeName="PSet_Application_CustomParamRectDuct" isDomainClass="True">
        <ECCustomAttributes>
            <ForceEntityClass xmlns="ECv3ConversionAttributes.01.00" />
        </ECCustomAttributes>
    </ECClass>
    <ECClass typeName="PSet_Application_CustomParamRectElbow" isDomainClass="True">
        <ECCustomAttributes>
            <ForceEntityClass xmlns="ECv3ConversionAttributes.01.00" />
        </ECCustomAttributes>
    </ECClass>
    <ECClass typeName="PSet_Application_CustomParamRectFireDamper" isDomainClass="True">
        <ECCustomAttributes>
            <ForceEntityClass xmlns="ECv3ConversionAttributes.01.00" />
        </ECCustomAttributes>
    </ECClass>
    <ECClass typeName="PSet_Application_CustomParamRectMeshGrille" isDomainClass="True">
        <ECCustomAttributes>
            <ForceEntityClass xmlns="ECv3ConversionAttributes.01.00" />
        </ECCustomAttributes>
    </ECClass>
    <ECClass typeName="PSet_Application_CustomParamRectOvalTransition" isDomainClass="True">
        <ECCustomAttributes>
            <ForceEntityClass xmlns="ECv3ConversionAttributes.01.00" />
        </ECCustomAttributes>
    </ECClass>
    <ECClass typeName="PSet_Application_CustomParamRectRndTransition" isDomainClass="True">
        <ECCustomAttributes>
            <ForceEntityClass xmlns="ECv3ConversionAttributes.01.00" />
        </ECCustomAttributes>
    </ECClass>
    <ECClass typeName="PSet_Application_CustomParamRectTakeoff" isDomainClass="True">
        <ECCustomAttributes>
            <ForceEntityClass xmlns="ECv3ConversionAttributes.01.00" />
        </ECCustomAttributes>
    </ECClass>
    <ECClass typeName="PSet_Application_CustomParamRectTransition" isDomainClass="True">
        <ECCustomAttributes>
            <ForceEntityClass xmlns="ECv3ConversionAttributes.01.00" />
        </ECCustomAttributes>
    </ECClass>
    <ECClass typeName="PSet_Application_CustomParamRoundDuct" isDomainClass="True">
        <ECCustomAttributes>
            <ForceEntityClass xmlns="ECv3ConversionAttributes.01.00" />
        </ECCustomAttributes>
    </ECClass>
    <ECClass typeName="PSet_Application_CustomParamRoundElbow" isDomainClass="True">
        <ECCustomAttributes>
            <ForceEntityClass xmlns="ECv3ConversionAttributes.01.00" />
        </ECCustomAttributes>
    </ECClass>
    <ECClass typeName="PSet_Application_CustomParamRoundTransition" isDomainClass="True">
        <ECCustomAttributes>
            <ForceEntityClass xmlns="ECv3ConversionAttributes.01.00" />
        </ECCustomAttributes>
    </ECClass>
    <ECClass typeName="PSet_Application_CustomParamSilencer" isDomainClass="True">
        <ECCustomAttributes>
            <ForceEntityClass xmlns="ECv3ConversionAttributes.01.00" />
        </ECCustomAttributes>
    </ECClass>
    <ECClass typeName="PSet_Application_CustomParamTakeoff" isDomainClass="True">
        <ECCustomAttributes>
            <ForceEntityClass xmlns="ECv3ConversionAttributes.01.00" />
        </ECCustomAttributes>
    </ECClass>
    <ECClass typeName="PSet_Application_Discipline" isDomainClass="True">
        <ECCustomAttributes>
            <ForceEntityClass xmlns="ECv3ConversionAttributes.01.00" />
        </ECCustomAttributes>
    </ECClass>
    <ECClass typeName="PSet_Application__Draughting" isDomainClass="True">
        <ECCustomAttributes>
            <ForceEntityClass xmlns="ECv3ConversionAttributes.01.00" />
        </ECCustomAttributes>
    </ECClass>
    <ECClass typeName="PSet_Application__name" isDomainClass="True">
        <ECCustomAttributes>
            <ForceEntityClass xmlns="ECv3ConversionAttributes.01.00" />
        </ECCustomAttributes>
    </ECClass>
    <ECClass typeName="PSet_Application_ArchDoor" isDomainClass="True">
        <ECCustomAttributes>
            <ForceEntityClass xmlns="ECv3ConversionAttributes.01.00" />
        </ECCustomAttributes>
    </ECClass>
    <ECClass typeName="PSet_Application_ArchSpace" isDomainClass="True">
        <ECCustomAttributes>
            <ForceEntityClass xmlns="ECv3ConversionAttributes.01.00" />
        </ECCustomAttributes>
    </ECClass>
    <ECClass typeName="PSet_Application_ArchWallCasework" isDomainClass="True">
        <ECCustomAttributes>
            <ForceEntityClass xmlns="ECv3ConversionAttributes.01.00" />
        </ECCustomAttributes>
    </ECClass>
    <ECClass typeName="PSet_Application_ArchWindow" isDomainClass="True">
        <ECCustomAttributes>
            <ForceEntityClass xmlns="ECv3ConversionAttributes.01.00" />
        </ECCustomAttributes>
    </ECClass>
    <ECClass typeName="PSet_Application_Constraints" isDomainClass="True">
        <ECCustomAttributes>
            <ForceEntityClass xmlns="ECv3ConversionAttributes.01.00" />
        </ECCustomAttributes>
    </ECClass>
    <ECClass typeName="PSet_Application_Construction" isDomainClass="True">
        <ECCustomAttributes>
            <ForceEntityClass xmlns="ECv3ConversionAttributes.01.00" />
        </ECCustomAttributes>
    </ECClass>
    <ECClass typeName="PSet_Application_Dimensions" isDomainClass="True">
        <ECCustomAttributes>
            <ForceEntityClass xmlns="ECv3ConversionAttributes.01.00" />
        </ECCustomAttributes>
    </ECClass>
    <ECClass typeName="PSet_Application_Electrical" isDomainClass="True">
        <ECCustomAttributes>
            <ForceEntityClass xmlns="ECv3ConversionAttributes.01.00" />
        </ECCustomAttributes>
    </ECClass>
    <ECClass typeName="PSet_Application_Electrical___Interlocked_W" isDomainClass="True">
        <ECCustomAttributes>
            <ForceEntityClass xmlns="ECv3ConversionAttributes.01.00" />
        </ECCustomAttributes>
    </ECClass>
    <ECClass typeName="PSet_Application_Electrical___Loads" isDomainClass="True">
        <ECCustomAttributes>
            <ForceEntityClass xmlns="ECv3ConversionAttributes.01.00" />
        </ECCustomAttributes>
    </ECClass>
    <ECClass typeName="PSet_Application_End1" isDomainClass="True">
        <ECCustomAttributes>
            <ForceEntityClass xmlns="ECv3ConversionAttributes.01.00" />
        </ECCustomAttributes>
    </ECClass>
    <ECClass typeName="PSet_Application_End2" isDomainClass="True">
        <ECCustomAttributes>
            <ForceEntityClass xmlns="ECv3ConversionAttributes.01.00" />
        </ECCustomAttributes>
    </ECClass>
    <ECClass typeName="PSet_Application_End3" isDomainClass="True">
        <ECCustomAttributes>
            <ForceEntityClass xmlns="ECv3ConversionAttributes.01.00" />
        </ECCustomAttributes>
    </ECClass>
    <ECClass typeName="PSet_Application_EndSpec1_1" isDomainClass="True">
        <ECCustomAttributes>
            <ForceEntityClass xmlns="ECv3ConversionAttributes.01.00" />
        </ECCustomAttributes>
    </ECClass>
    <ECClass typeName="PSet_Application_EndSpec1_2" isDomainClass="True">
        <ECCustomAttributes>
            <ForceEntityClass xmlns="ECv3ConversionAttributes.01.00" />
        </ECCustomAttributes>
    </ECClass>
    <ECClass typeName="PSet_Application_EndSpec1_3" isDomainClass="True">
        <ECCustomAttributes>
            <ForceEntityClass xmlns="ECv3ConversionAttributes.01.00" />
        </ECCustomAttributes>
    </ECClass>
    <ECClass typeName="PSet_Application_EndSpec2_11" isDomainClass="True">
        <ECCustomAttributes>
            <ForceEntityClass xmlns="ECv3ConversionAttributes.01.00" />
        </ECCustomAttributes>
    </ECClass>
    <ECClass typeName="PSet_Application_EndSpec2_12" isDomainClass="True">
        <ECCustomAttributes>
            <ForceEntityClass xmlns="ECv3ConversionAttributes.01.00" />
        </ECCustomAttributes>
    </ECClass>
    <ECClass typeName="PSet_Application_EndSpec2_13" isDomainClass="True">
        <ECCustomAttributes>
            <ForceEntityClass xmlns="ECv3ConversionAttributes.01.00" />
        </ECCustomAttributes>
    </ECClass>
    <ECClass typeName="PSet_Application_EndSpec2_22" isDomainClass="True">
        <ECCustomAttributes>
            <ForceEntityClass xmlns="ECv3ConversionAttributes.01.00" />
        </ECCustomAttributes>
    </ECClass>
    <ECClass typeName="PSet_Application_EndSpec2_33" isDomainClass="True">
        <ECCustomAttributes>
            <ForceEntityClass xmlns="ECv3ConversionAttributes.01.00" />
        </ECCustomAttributes>
    </ECClass>
    <ECClass typeName="PSet_Application_EndSpec3_111" isDomainClass="True">
        <ECCustomAttributes>
            <ForceEntityClass xmlns="ECv3ConversionAttributes.01.00" />
        </ECCustomAttributes>
    </ECClass>
    <ECClass typeName="PSet_Application_EndSpec3_112" isDomainClass="True">
        <ECCustomAttributes>
            <ForceEntityClass xmlns="ECv3ConversionAttributes.01.00" />
        </ECCustomAttributes>
    </ECClass>
    <ECClass typeName="PSet_Application_EndSpec3_113" isDomainClass="True">
        <ECCustomAttributes>
            <ForceEntityClass xmlns="ECv3ConversionAttributes.01.00" />
        </ECCustomAttributes>
    </ECClass>
    <ECClass typeName="PSet_Application_EndSpec3_331" isDomainClass="True">
        <ECCustomAttributes>
            <ForceEntityClass xmlns="ECv3ConversionAttributes.01.00" />
        </ECCustomAttributes>
    </ECClass>
    <ECClass typeName="PSet_Application_EndSpec3_333" isDomainClass="True">
        <ECCustomAttributes>
            <ForceEntityClass xmlns="ECv3ConversionAttributes.01.00" />
        </ECCustomAttributes>
    </ECClass>
    <ECClass typeName="PSet_Application_Floor" isDomainClass="True">
        <ECCustomAttributes>
            <ForceEntityClass xmlns="ECv3ConversionAttributes.01.00" />
        </ECCustomAttributes>
    </ECClass>
    <ECClass typeName="PSet_Application_General" isDomainClass="True">
        <ECCustomAttributes>
            <ForceEntityClass xmlns="ECv3ConversionAttributes.01.00" />
        </ECCustomAttributes>
    </ECClass>
    <ECClass typeName="PSet_Application_Graphics" isDomainClass="True">
        <ECCustomAttributes>
            <ForceEntityClass xmlns="ECv3ConversionAttributes.01.00" />
        </ECCustomAttributes>
    </ECClass>
    <ECClass typeName="PSet_Application_Graphisoft_AC81_DOOR" isDomainClass="True">
        <ECCustomAttributes>
            <ForceEntityClass xmlns="ECv3ConversionAttributes.01.00" />
        </ECCustomAttributes>
    </ECClass>
    <ECClass typeName="PSet_Application_Graphisoft_AC81_SLAB" isDomainClass="True">
        <ECCustomAttributes>
            <ForceEntityClass xmlns="ECv3ConversionAttributes.01.00" />
        </ECCustomAttributes>
    </ECClass>
    <ECClass typeName="PSet_Application_Graphisoft_AC81_SPACE" isDomainClass="True">
        <ECCustomAttributes>
            <ForceEntityClass xmlns="ECv3ConversionAttributes.01.00" />
        </ECCustomAttributes>
    </ECClass>
    <ECClass typeName="PSet_Application_Graphisoft_AC81_WALL" isDomainClass="True">
        <ECCustomAttributes>
            <ForceEntityClass xmlns="ECv3ConversionAttributes.01.00" />
        </ECCustomAttributes>
    </ECClass>
    <ECClass typeName="PSet_Application_Graphisoft_AC81_WINDOW" isDomainClass="True">
        <ECCustomAttributes>
            <ForceEntityClass xmlns="ECv3ConversionAttributes.01.00" />
        </ECCustomAttributes>
    </ECClass>
    <ECClass typeName="PSet_Application_Identification" isDomainClass="True">
        <ECCustomAttributes>
            <ForceEntityClass xmlns="ECv3ConversionAttributes.01.00" />
        </ECCustomAttributes>
    </ECClass>
    <ECClass typeName="PSet_Application_Identity_Data" isDomainClass="True">
        <ECCustomAttributes>
            <ForceEntityClass xmlns="ECv3ConversionAttributes.01.00" />
        </ECCustomAttributes>
    </ECClass>
    <ECClass typeName="PSet_Application_InsulationSymbology" isDomainClass="True">
        <ECCustomAttributes>
            <ForceEntityClass xmlns="ECv3ConversionAttributes.01.00" />
        </ECCustomAttributes>
    </ECClass>
    <ECClass typeName="PSet_Application_Mechanical" isDomainClass="True">
        <ECCustomAttributes>
            <ForceEntityClass xmlns="ECv3ConversionAttributes.01.00" />
        </ECCustomAttributes>
    </ECClass>
    <ECClass typeName="PSet_Application_Mechanical___Flow" isDomainClass="True">
        <ECCustomAttributes>
            <ForceEntityClass xmlns="ECv3ConversionAttributes.01.00" />
        </ECCustomAttributes>
    </ECClass>
    <ECClass typeName="PSet_Application_ObjectClassification" isDomainClass="True">
        <ECCustomAttributes>
            <ForceEntityClass xmlns="ECv3ConversionAttributes.01.00" />
        </ECCustomAttributes>
    </ECClass>
    <ECClass typeName="PSet_Application_ObjectPostalAddress" isDomainClass="True">
        <ECCustomAttributes>
            <ForceEntityClass xmlns="ECv3ConversionAttributes.01.00" />
        </ECCustomAttributes>
    </ECClass>
    <ECClass typeName="PSet_Application_Other" isDomainClass="True">
        <ECCustomAttributes>
            <ForceEntityClass xmlns="ECv3ConversionAttributes.01.00" />
        </ECCustomAttributes>
    </ECClass>
    <ECClass typeName="PSet_Application_ParaDef" isDomainClass="True">
        <ECCustomAttributes>
            <ForceEntityClass xmlns="ECv3ConversionAttributes.01.00" />
        </ECCustomAttributes>
    </ECClass>
    <ECClass typeName="PSet_Application_Phasing" isDomainClass="True">
        <ECCustomAttributes>
            <ForceEntityClass xmlns="ECv3ConversionAttributes.01.00" />
        </ECCustomAttributes>
    </ECClass>
    <ECClass typeName="PSet_Application_PISARA_M__R_" isDomainClass="True">
        <ECCustomAttributes>
            <ForceEntityClass xmlns="ECv3ConversionAttributes.01.00" />
        </ECCustomAttributes>
    </ECClass>
    <ECClass typeName="PSet_Application_PISARA_SIJAINTI" isDomainClass="True">
        <ECCustomAttributes>
            <ForceEntityClass xmlns="ECv3ConversionAttributes.01.00" />
        </ECCustomAttributes>
    </ECClass>
    <ECClass typeName="PSet_Application_PISARA_TIETO" isDomainClass="True">
        <ECCustomAttributes>
            <ForceEntityClass xmlns="ECv3ConversionAttributes.01.00" />
        </ECCustomAttributes>
    </ECClass>
    <ECClass typeName="PSet_Application_PISARA_VANHAT_RAKENTEET" isDomainClass="True">
        <ECCustomAttributes>
            <ForceEntityClass xmlns="ECv3ConversionAttributes.01.00" />
        </ECCustomAttributes>
    </ECClass>
    <ECClass typeName="PSet_Application_Project" isDomainClass="True">
        <ECCustomAttributes>
            <ForceEntityClass xmlns="ECv3ConversionAttributes.01.00" />
        </ECCustomAttributes>
    </ECClass>
    <ECClass typeName="PSet_Application_Properties" isDomainClass="True">
        <ECCustomAttributes>
            <ForceEntityClass xmlns="ECv3ConversionAttributes.01.00" />
        </ECCustomAttributes>
    </ECClass>
    <ECClass typeName="PSet_Application_R" isDomainClass="True">
        <ECCustomAttributes>
            <ForceEntityClass xmlns="ECv3ConversionAttributes.01.00" />
        </ECCustomAttributes>
    </ECClass>
    <ECClass typeName="PSet_Application_ReturnFanData" isDomainClass="True">
        <ECCustomAttributes>
            <ForceEntityClass xmlns="ECv3ConversionAttributes.01.00" />
        </ECCustomAttributes>
    </ECClass>
    <ECClass typeName="PSet_Application__Revit_Constraints" isDomainClass="True">
        <ECCustomAttributes>
            <ForceEntityClass xmlns="ECv3ConversionAttributes.01.00" />
        </ECCustomAttributes>
    </ECClass>
    <ECClass typeName="PSet_Application__Revit_Construction" isDomainClass="True">
        <ECCustomAttributes>
            <ForceEntityClass xmlns="ECv3ConversionAttributes.01.00" />
        </ECCustomAttributes>
    </ECClass>
    <ECClass typeName="PSet_Application__Revit_Dimensions" isDomainClass="True">
        <ECCustomAttributes>
            <ForceEntityClass xmlns="ECv3ConversionAttributes.01.00" />
        </ECCustomAttributes>
    </ECClass>
    <ECClass typeName="PSet_Application__Revit_Identity_Data" isDomainClass="True">
        <ECCustomAttributes>
            <ForceEntityClass xmlns="ECv3ConversionAttributes.01.00" />
        </ECCustomAttributes>
    </ECClass>
    <ECClass typeName="PSet_Application__Revit_Materials_and_Finishes" isDomainClass="True">
        <ECCustomAttributes>
            <ForceEntityClass xmlns="ECv3ConversionAttributes.01.00" />
        </ECCustomAttributes>
    </ECClass>
    <ECClass typeName="PSet_Application__Revit_Other" isDomainClass="True">
        <ECCustomAttributes>
            <ForceEntityClass xmlns="ECv3ConversionAttributes.01.00" />
        </ECCustomAttributes>
    </ECClass>
    <ECClass typeName="PSet_Application__Revit_Phasing" isDomainClass="True">
        <ECCustomAttributes>
            <ForceEntityClass xmlns="ECv3ConversionAttributes.01.00" />
        </ECCustomAttributes>
    </ECClass>
    <ECClass typeName="PSet_Application__Revit_Profile" isDomainClass="True">
        <ECCustomAttributes>
            <ForceEntityClass xmlns="ECv3ConversionAttributes.01.00" />
        </ECCustomAttributes>
    </ECClass>
    <ECClass typeName="PSet_Application__Revit_Slab_Shape_Edit" isDomainClass="True">
        <ECCustomAttributes>
            <ForceEntityClass xmlns="ECv3ConversionAttributes.01.00" />
        </ECCustomAttributes>
    </ECClass>
    <ECClass typeName="PSet_Application__Revit_Structural" isDomainClass="True">
        <ECCustomAttributes>
            <ForceEntityClass xmlns="ECv3ConversionAttributes.01.00" />
        </ECCustomAttributes>
    </ECClass>
    <ECClass typeName="PSet_Application__Revit_Type_Constraints" isDomainClass="True">
        <ECCustomAttributes>
            <ForceEntityClass xmlns="ECv3ConversionAttributes.01.00" />
        </ECCustomAttributes>
    </ECClass>
    <ECClass typeName="PSet_Application__Revit_Type_Construction" isDomainClass="True">
        <ECCustomAttributes>
            <ForceEntityClass xmlns="ECv3ConversionAttributes.01.00" />
        </ECCustomAttributes>
    </ECClass>
    <ECClass typeName="PSet_Application__Revit_Type_Dimensions" isDomainClass="True">
        <ECCustomAttributes>
            <ForceEntityClass xmlns="ECv3ConversionAttributes.01.00" />
        </ECCustomAttributes>
    </ECClass>
    <ECClass typeName="PSet_Application__Revit_Type_Graphics" isDomainClass="True">
        <ECCustomAttributes>
            <ForceEntityClass xmlns="ECv3ConversionAttributes.01.00" />
        </ECCustomAttributes>
    </ECClass>
    <ECClass typeName="PSet_Application__Revit_Type_Identity_Data" isDomainClass="True">
        <ECCustomAttributes>
            <ForceEntityClass xmlns="ECv3ConversionAttributes.01.00" />
        </ECCustomAttributes>
    </ECClass>
    <ECClass typeName="PSet_Application__Revit_Type_Other" isDomainClass="True">
        <ECCustomAttributes>
            <ForceEntityClass xmlns="ECv3ConversionAttributes.01.00" />
        </ECCustomAttributes>
    </ECClass>
    <ECClass typeName="PSet_Application__Revit_Type_Structural" isDomainClass="True">
        <ECCustomAttributes>
            <ForceEntityClass xmlns="ECv3ConversionAttributes.01.00" />
        </ECCustomAttributes>
    </ECClass>
    <ECClass typeName="PSet_Application_Site" isDomainClass="True">
        <ECCustomAttributes>
            <ForceEntityClass xmlns="ECv3ConversionAttributes.01.00" />
        </ECCustomAttributes>
    </ECClass>
    <ECClass typeName="PSet_Application_StructuralFloorCommon" isDomainClass="True">
        <ECCustomAttributes>
            <ForceEntityClass xmlns="ECv3ConversionAttributes.01.00" />
        </ECCustomAttributes>
    </ECClass>
    <ECClass typeName="PSet_Application_StructuralFramingCommon" isDomainClass="True">
        <ECCustomAttributes>
            <ForceEntityClass xmlns="ECv3ConversionAttributes.01.00" />
        </ECCustomAttributes>
    </ECClass>
    <ECClass typeName="PSet_Application_Technip_settings" isDomainClass="True">
        <ECCustomAttributes>
            <ForceEntityClass xmlns="ECv3ConversionAttributes.01.00" />
        </ECCustomAttributes>
    </ECClass>
    <ECClass typeName="PSet_Application_Tekla_Assembly" isDomainClass="True">
        <ECCustomAttributes>
            <ForceEntityClass xmlns="ECv3ConversionAttributes.01.00" />
        </ECCustomAttributes>
    </ECClass>
    <ECClass typeName="PSet_Application_Tekla_Bolt" isDomainClass="True">
        <ECCustomAttributes>
            <ForceEntityClass xmlns="ECv3ConversionAttributes.01.00" />
        </ECCustomAttributes>
    </ECClass>
    <ECClass typeName="PSet_Application_Tekla_Common" isDomainClass="True">
        <ECCustomAttributes>
            <ForceEntityClass xmlns="ECv3ConversionAttributes.01.00" />
        </ECCustomAttributes>
    </ECClass>
    <ECClass typeName="PSet_Application_Tekla_Reinforcement" isDomainClass="True">
        <ECCustomAttributes>
            <ForceEntityClass xmlns="ECv3ConversionAttributes.01.00" />
        </ECCustomAttributes>
    </ECClass>
    <ECClass typeName="PSet_Application_Tekla_Quantity" isDomainClass="True">
        <ECCustomAttributes>
            <ForceEntityClass xmlns="ECv3ConversionAttributes.01.00" />
        </ECCustomAttributes>
    </ECClass>
    <ECClass typeName="PSet_Application_us_ncs_CurtainWalls" isDomainClass="True">
        <ECCustomAttributes>
            <ForceEntityClass xmlns="ECv3ConversionAttributes.01.00" />
        </ECCustomAttributes>
    </ECClass>
    <ECClass typeName="PSet_Application_us_ncs_Door" isDomainClass="True">
        <ECCustomAttributes>
            <ForceEntityClass xmlns="ECv3ConversionAttributes.01.00" />
        </ECCustomAttributes>
    </ECClass>
    <ECClass typeName="PSet_Application_us_ncs_PlumbingFixtures" isDomainClass="True">
        <ECCustomAttributes>
            <ForceEntityClass xmlns="ECv3ConversionAttributes.01.00" />
        </ECCustomAttributes>
    </ECClass>
    <ECClass typeName="PSet_Application_us_ncs_Shelving" isDomainClass="True">
        <ECCustomAttributes>
            <ForceEntityClass xmlns="ECv3ConversionAttributes.01.00" />
        </ECCustomAttributes>
    </ECClass>
    <ECClass typeName="PSet_Application_us_ncs_Space" isDomainClass="True">
        <ECCustomAttributes>
            <ForceEntityClass xmlns="ECv3ConversionAttributes.01.00" />
        </ECCustomAttributes>
    </ECClass>
    <ECClass typeName="PSet_Application_us_ncs_WallCasework" isDomainClass="True">
        <ECCustomAttributes>
            <ForceEntityClass xmlns="ECv3ConversionAttributes.01.00" />
        </ECCustomAttributes>
    </ECClass>
    <ECClass typeName="PSet_Application_us_ncs_Window" isDomainClass="True">
        <ECCustomAttributes>
            <ForceEntityClass xmlns="ECv3ConversionAttributes.01.00" />
        </ECCustomAttributes>
    </ECClass>
    <ECClass typeName="PSetComplex_Application__1" isDomainClass="True">
        <ECCustomAttributes>
            <ForceEntityClass xmlns="ECv3ConversionAttributes.01.00" />
        </ECCustomAttributes>
    </ECClass>
    <ECClass typeName="PSetComplex_Application__2" isDomainClass="True">
        <ECCustomAttributes>
            <ForceEntityClass xmlns="ECv3ConversionAttributes.01.00" />
        </ECCustomAttributes>
    </ECClass>
    <ECClass typeName="PSetComplex_Application__3" isDomainClass="True">
        <ECCustomAttributes>
            <ForceEntityClass xmlns="ECv3ConversionAttributes.01.00" />
        </ECCustomAttributes>
    </ECClass>
    <ECClass typeName="PSetComplex_Application_arr" isDomainClass="True">
        <ECCustomAttributes>
            <ForceEntityClass xmlns="ECv3ConversionAttributes.01.00" />
        </ECCustomAttributes>
    </ECClass>
    <ECClass typeName="PSetComplex_Application_Color" isDomainClass="True">
        <ECCustomAttributes>
            <ForceEntityClass xmlns="ECv3ConversionAttributes.01.00" />
        </ECCustomAttributes>
    </ECClass>
    <ECClass typeName="PSetComplex_Application_Colour" isDomainClass="True">
        <ECCustomAttributes>
            <ForceEntityClass xmlns="ECv3ConversionAttributes.01.00" />
        </ECCustomAttributes>
    </ECClass>
    <ECClass typeName="PSetComplex_Application_DOOR" isDomainClass="True">
        <ECCustomAttributes>
            <ForceEntityClass xmlns="ECv3ConversionAttributes.01.00" />
        </ECCustomAttributes>
    </ECClass>
    <ECClass typeName="PSetComplex_Application_horgrid" isDomainClass="True">
        <ECCustomAttributes>
            <ForceEntityClass xmlns="ECv3ConversionAttributes.01.00" />
        </ECCustomAttributes>
    </ECClass>
    <ECClass typeName="PSetComplex_Application_LIBPARAM" isDomainClass="True">
        <ECCustomAttributes>
            <ForceEntityClass xmlns="ECv3ConversionAttributes.01.00" />
        </ECCustomAttributes>
    </ECClass>
    <ECClass typeName="PSetComplex_Application_SLAB" isDomainClass="True">
        <ECCustomAttributes>
            <ForceEntityClass xmlns="ECv3ConversionAttributes.01.00" />
        </ECCustomAttributes>
    </ECClass>
    <ECClass typeName="PSetComplex_Application_SPACE" isDomainClass="True">
        <ECCustomAttributes>
            <ForceEntityClass xmlns="ECv3ConversionAttributes.01.00" />
        </ECCustomAttributes>
    </ECClass>
    <ECClass typeName="PSetComplex_Application_vergrid" isDomainClass="True">
        <ECCustomAttributes>
            <ForceEntityClass xmlns="ECv3ConversionAttributes.01.00" />
        </ECCustomAttributes>
    </ECClass>
    <ECClass typeName="PSetComplex_Application_WALL" isDomainClass="True">
        <ECCustomAttributes>
            <ForceEntityClass xmlns="ECv3ConversionAttributes.01.00" />
        </ECCustomAttributes>
    </ECClass>
    <ECClass typeName="PSetComplex_Application_WINDOW" isDomainClass="True">
        <ECCustomAttributes>
            <ForceEntityClass xmlns="ECv3ConversionAttributes.01.00" />
        </ECCustomAttributes>
    </ECClass>

</ECSchema>

